gatherer/__init__.py
gatherer/bigboat.py
gatherer/config.py
gatherer/database.py
gatherer/files.py
gatherer/jenkins.py
gatherer/log.py
gatherer/py.typed
gatherer/request.py
gatherer/salt.py
gatherer/table.py
gatherer/update.py
gatherer/utils.py
gatherer/domain/__init__.py
gatherer/domain/project.py
gatherer/domain/sources.py
gatherer/domain/source/__init__.py
gatherer/domain/source/controller.py
gatherer/domain/source/git.py
gatherer/domain/source/github.py
gatherer/domain/source/gitlab.py
gatherer/domain/source/jenkins.py
gatherer/domain/source/jira.py
gatherer/domain/source/quality_time.py
gatherer/domain/source/sonar.py
gatherer/domain/source/svn.py
gatherer/domain/source/tfs.py
gatherer/domain/source/types.py
gatherer/git/__init__.py
gatherer/git/github.py
gatherer/git/gitlab.py
gatherer/git/progress.py
gatherer/git/repo.py
gatherer/git/tfs.py
gatherer/jira/__init__.py
gatherer/jira/base.py
gatherer/jira/changelog.py
gatherer/jira/collector.py
gatherer/jira/field.py
gatherer/jira/parser.py
gatherer/jira/query.py
gatherer/jira/special_field.py
gatherer/jira/update.py
gatherer/project_definition/__init__.py
gatherer/project_definition/base.py
gatherer/project_definition/collector.py
gatherer/project_definition/metric.py
gatherer/project_definition/update.py
gatherer/project_definition/quality_time/__init__.py
gatherer/project_definition/quality_time/data.py
gatherer/project_definition/quality_time/parser.py
gatherer/project_definition/sonar/__init__.py
gatherer/project_definition/sonar/data.py
gatherer/project_definition/sonar/parser.py
gatherer/svn/__init__.py
gatherer/svn/difference.py
gatherer/svn/repo.py
gatherer/version_control/__init__.py
gatherer/version_control/holder.py
gatherer/version_control/repo.py
gatherer/version_control/review.py
gatherer/vsts/__init__.py
gatherer/vsts/parser.py
gros_gatherer-1.0.0.dist-info/LICENSE
gros_gatherer-1.0.0.dist-info/METADATA
gros_gatherer-1.0.0.dist-info/WHEEL
gros_gatherer-1.0.0.dist-info/top_level.txt
gros_gatherer-1.0.0.dist-info/RECORD
