Metadata-Version: 2.1
Name: gros-gatherer
Version: 1.0.0
Summary: Software development process data gathering
Author-email: Leon Helwerda <l.s.helwerda@liacs.leidenuniv.nl>
License: Apache 2.0
Project-URL: Homepage, https://gros.liacs.nl
Project-URL: Documentation, https://gros.liacs.nl/data-gathering/
Project-URL: PyPI, https://pypi.python.org/pypi/gros-gatherer
Project-URL: Source Code, https://github.com/grip-on-software/data-gathering
Project-URL: Issues, https://github.com/grip-on-software/data-gathering/issues
Project-URL: Pull Requests, https://github.com/grip-on-software/data-gathering/pulls
Project-URL: CI: GitHub Actions, https://github.com/grip-on-software/data-gathering/actions
Project-URL: CI: Coveralls, https://coveralls.io/github/grip-on-software/data-gathering?branch=master
Project-URL: CI: SonarCloud, https://sonarcloud.io/project/overview?id=grip-on-software_data-gathering
Keywords: software development process,data gathering
Classifier: Development Status :: 5 - Production/Stable
Classifier: Environment :: Console
Classifier: Environment :: Web Environment
Classifier: Intended Audience :: Developers
Classifier: Intended Audience :: Information Technology
Classifier: Topic :: Software Development :: Bug Tracking
Classifier: Topic :: Software Development :: Build Tools
Classifier: Topic :: Software Development :: Quality Assurance
Classifier: Topic :: Software Development :: Version Control :: Git
Classifier: Topic :: System :: Distributed Computing
Classifier: Topic :: System :: Monitoring
Classifier: License :: OSI Approved :: Apache Software License
Classifier: Programming Language :: Python :: 3
Classifier: Programming Language :: Python :: 3.8
Classifier: Programming Language :: Python :: 3.9
Classifier: Programming Language :: Python :: 3.10
Classifier: Programming Language :: Python :: 3.11
Classifier: Programming Language :: Python :: 3.12
Requires-Python: >=3.8
License-File: LICENSE
Requires-Dist: urlmatch ==1.0.1
Requires-Dist: jira ==3.8.0
Requires-Dist: GitPython ==3.1.43
Requires-Dist: PyGithub ==2.3.0
Requires-Dist: python-gitlab ==4.4.0
Requires-Dist: ordered-set ==4.1.0
Requires-Dist: svn ==1.0.1
Requires-Dist: packaging ==24.0
Requires-Dist: requests ==2.31.0
Requires-Dist: requests-ntlm ==1.2.0
Requires-Dist: pymonetdb ==1.8.1
Requires-Dist: pyocclient ==0.6
Requires-Dist: bcrypt ==4.1.2
